password_generator_gtk-0.1.dist-info/top_level.txt
password_generator_gtk-0.1.dist-info/RECORD
password_generator_gtk-0.1.dist-info/WHEEL
password_generator_gtk-0.1.dist-info/metadata.json
password_generator_gtk-0.1.dist-info/METADATA
password_generator_gtk-0.1.dist-info/DESCRIPTION.rst
password_generator_gtk-0.1.data/scripts/pasgen
passwordgeneratorgtk/__init__.py
passwordgeneratorgtk/pasgen.glade
passwordgeneratorgtk/pasgen.py
