Metadata-Version: 2.0
Name: password-generator-gtk
Version: 0.1
Summary: Little Linux Password Generator written on Python 3 with Gtk
Home-page: https://github.com/wirbi7/password-generator
Author: Igor Nekrasov
Author-email: nekrasov.i.m@gmail.com
License: GNU GPL 2.0
Platform: UNKNOWN
Classifier: Development Status :: 4 - Beta
Classifier: Intended Audience :: End Users/Desktop
Classifier: Operating System :: POSIX
Classifier: Programming Language :: Python
